Workbook

Sheet About
A1: Project 02 — Accounts Receivable & Cash Flow Dashboard
A2: Portfolio project using FICTIONAL data for a fictional company (Northwind Field Services LLC). Not real employment results.
A4: Purpose
A5: Analyse receivables, ageing, collection performance (DSO, CEI) and forecast cash inflows for the next 3 months.
A7: How the workbook works
A8: 1. Assumptions — report date, ageing buckets, collection probabilities (yellow cells are editable inputs).
A9: 2. Customers — customer master with payment terms and credit limits (blue = inputs).
A10: 3. Invoices — invoice register; due date, outstanding, days past due and ageing bucket are formulas.
A11: 4. AR_Aging — ageing by customer with credit-limit check (SUMIFS formulas).
A12: 5. Collections_KPI — monthly billing vs collections, DSO and Collection Effectiveness Index.
A13: 6. Cash_Forecast — expected collections by month weighted by bucket-level collection probability.
A14: 7. Dashboard — headline KPIs and charts.
... A19: Tools: Microsoft Excel (SUMIFS, INDEX/MATCH, IF logic, charts). Author: Muhammed Shabeeb MK

Sheet Dashboard
A1: AR & Cash Flow Dashboard — Northwind Field Services LLC (fictional)
A2: As of | B2: =Assumptions!$B$2 -> 46022
A4: Total AR ($) | B4: =Collections_KPI!B16 -> 757250 | D4: Overdue AR ($) | E4: =Collections_KPI!B19 -> 266070
A6: % AR overdue | B6: =Collections_KPI!B20 -> 0.35136349 | D6: DSO (days) | E6: =Collections_KPI!B18 -> 64.223317
A8: AR over 90 days ($) | B8: =Collections_KPI!B21 -> 47560 | D8: 6-month CEI | E8: =Collections_KPI!B25 -> 0.62781199
A10: Expected collections next 3 months ($) | B10: =Cash_Forecast!E9 -> 694872.9 | D10: At-risk balance ($) | E10: =Cash_Forecast!B11 -> 62377.1

Sheet Assumptions
A1: Assumption | B1: Value | C1: Note
A2: Report (as-of) date | B2: 46022 | C2: Ageing and DSO measured at this date
A3: DSO lookback period (days) | B3: 90 | C3: Days used in DSO = AR / credit sales × days
A4: Collection probability – Not yet due | B4: 0.98 | C4: Share of open balance expected to be collected
A5: Collection probability – 1-30 days | B5: 0.95
A6: Collection probability – 31-60 days | B6: 0.85
A7: Collection probability – 61-90 days | B7: 0.65
A8: Collection probability – 90+ days | B8: 0.3 | C8: Remainder treated as at-risk / provision candidate
A9: Delay after due date – overdue items (days) | B9: 30 | C9: Overdue balances assumed collected this many days after report date
A10: Currency | B10: USD | C10: All amounts in US dollars (fictional)
A12: Ageing bucket labels
A13: Not due
A14: 1-30
A15: 31-60
A16: 61-90
A17: 90+

Sheet Customers
A1: Customer ID | B1: Customer Name | C1: Segment | D1: Terms (days) | E1: Credit Limit ($)
A2: C001 | B2: Al Noor Construction | C2: Construction | D2: 30 | E2: 150000
A3: C002 | B3: Gulf Infra Projects | C3: Infrastructure | D3: 45 | E3: 250000
A4: C003 | B4: Metro Utilities Co | C4: Utilities | D4: 60 | E4: 200000
A5: C004 | B5: Desert Logistics | C5: Logistics | D5: 30 | E5: 80000
A6: C005 | B6: BlueWave Telecom | C6: Telecom | D6: 45 | E6: 120000
A7: C006 | B7: Harbor Developers | C7: Real Estate | D7: 60 | E7: 180000
A8: C007 | B8: Sunrise Facilities | C8: Facilities Mgmt | D8: 30 | E8: 60000
A9: C008 | B9: Coastal Roads Authority | C9: Government | D9: 90 | E9: 300000
A10: C009 | B10: Prime Events | C10: Events | D10: 15 | E10: 40000
A11: C010 | B11: Oasis Retail Group | C11: Retail | D11: 30 | E11: 70000

Sheet Invoices
A1: Invoice No | B1: Customer ID | C1: Customer Name | D1: Invoice Date | E1: Terms (days) | F1: Due Date | G1: Invoice Amount ($) | H1: Amount Paid ($) | I1: Payment Date | J1: Outstanding ($) | K1: Days Past Due | L1: Ageing Bucket | M1: Days to Pay
A2: INV-20250001 | B2: C009 | C2: =INDEX(Customers!$B$2:$B$11,MATCH(B2,Customers!$A$2:$A$11,0)) -> Prime Events | D2: 45839 | E2: =INDEX(Customers!$D$2:$D$11,MATCH(B2,Customers!$A$2:$A$11,0)) -> 15 | F2: =D2+E2 -> 45854 | G2: 38990 | H2: 38990 | I2: 45858 | J2: =G2-H2 -> 0 | K2: =IF(AND(J2>0,Assumptions!$B$2>F2),Assumptions!$B$2-F2,0) -> 0 | L2: =IF(J2<=0,"Paid",IF(K2=0,"Not due",IF(K2<=30,"1-30",IF(K2<=60,"31-60",IF(K2<=90,"61-90","90+"))))) -> Paid | M2: =IF(AND(J2<=0,I2<>""),I2-D2,"") -> 19
A3: INV-20250002 | B3: C009 | C3: =INDEX(Customers!$B$2:$B$11,MATCH(B3,Customers!$A$2:$A$11,0)) -> Prime Events | D3: 45839 | E3: =INDEX(Customers!$D$2:$D$11,MATCH(B3,Customers!$A$2:$A$11,0)) -> 15 | F3: =D3+E3 -> 45854 | G3: 22980 | H3: 22980 | I3: 45849 | J3: =G3-H3 -> 0 | K3: =IF(AND(J3>0,Assumptions!$B$2>F3),Assumptions!$B$2-F3,0) -> 0 | L3: =IF(J3<=0,"Paid",IF(K3=0,"Not due",IF(K3<=30,"1-30",IF(K3<=60,"31-60",IF(K3<=90,"61-90","90+"))))) -> Paid | M3: =IF(AND(J3<=0,I3<>""),I3-D3,"") -> 10
A4: INV-20250003 | B4: C005 | C4: =INDEX(Customers!$B$2:$B$11,MATCH(B4,Customers!$A$2:$A$11,0)) -> BlueWave Telecom | D4: 45842 | E4: =INDEX(Customers!$D$2:$D$11,MATCH(B4,Customers!$A$2:$A$11,0)) -> 45 | F4: =D4+E4 -> 45887 | G4: 8960 | H4: 8960 | I4: 45882 | J4: =G4-H4 -> 0 | K4: =IF(AND(J4>0,Assumptions!$B$2>F4),Assumptions!$B$2-F4,0) -> 0 | L4: =IF(J4<=0,"Paid",IF(K4=0,"Not due",IF(K4<=30,"1-30",IF(K4<=60,"31-60",IF(K4<=90,"61-90","90+"))))) -> Paid | M4: =IF(AND(J4<=0,I4<>""),I4-D4,"") -> 40
A5: INV-20250004 | B5: C007 | C5: =INDEX(Customers!$B$2:$B$11,MATCH(B5,Customers!$A$2:$A$11,0)) -> Sunrise Facilities | D5: 45842 | E5: =INDEX(Customers!$D$2:$D$11,MATCH(B5,Customers!$A$2:$A$11,0)) -> 30 | F5: =D5+E5 -> 45872 | G5: 43520 | H5: 43520 | I5: 45868 | J5: =G5-H5 -> 0 | K5: =IF(AND(J5>0,Assumptions!$B$2>F5),Assumptions!$B$2-F5,0) -> 0 | L5: =IF(J5<=0,"Paid",IF(K5=0,"Not due",IF(K5<=30,"1-30",IF(K5<=60,"31-60",IF(K5<=90,"61-90","90+"))))) -> Paid | M5: =IF(AND(J5<=0,I5<>""),I5-D5,"") -> 26
A6: INV-20250005 | B6: C010 | C6: =INDEX(Customers!$B$2:$B$11,MATCH(B6,Customers!$A$2:$A$11,0)) -> Oasis Retail Group | D6: 45845 | E6: =INDEX(Customers!$D$2:$D$11,MATCH(B6,Customers!$A$2:$A$11,0)) -> 30 | F6: =D6+E6 -> 45875 | G6: 3630 | H6: 3630 | I6: 45884 | J6: =G6-H6 -> 0 | K6: =IF(AND(J6>0,Assumptions!$B$2>F6),Assumptions!$B$2-F6,0) -> 0 | L6: =IF(J6<=0,"Paid",IF(K6=0,"Not due",IF(K6<=30,"1-30",IF(K6<=60,"31-60",IF(K6<=90,"61-90","90+"))))) -> Paid | M6: =IF(AND(J6<=0,I6<>""),I6-D6,"") -> 39
A7: INV-20250006 | B7: C008 | C7: =INDEX(Customers!$B$2:$B$11,MATCH(B7,Customers!$A$2:$A$11,0)) -> Coastal Roads Authority | D7: 45848 | E7: =INDEX(Customers!$D$2:$D$11,MATCH(B7,Customers!$A$2:$A$11,0)) -> 90 | F7: =D7+E7 -> 45938 | G7: 16700 | H7: 16700 | I7: 45982 | J7: =G7-H7 -> 0 | K7: =IF(AND(J7>0,Assumptions!$B$2>F7),Assumptions!$B$2-F7,0) -> 0 | L7: =IF(J7<=0,"Paid",IF(K7=0,"Not due",IF(K7<=30,"1-30",IF(K7<=60,"31-60",IF(K7<=90,"61-90","90+"))))) -> Paid | M7: =IF(AND(J7<=0,I7<>""),I7-D7,"") -> 134
A8: INV-20250007 | B8: C005 | C8: =INDEX(Customers!$B$2:$B$11,MATCH(B8,Customers!$A$2:$A$11,0)) -> BlueWave Telecom | D8: 45851 | E8: =INDEX(Customers!$D$2:$D$11,MATCH(B8,Customers!$A$2:$A$11,0)) -> 45 | F8: =D8+E8 -> 45896 | G8: 23990 | H8: 23990 | I8: 45901 | J8: =G8-H8 -> 0 | K8: =IF(AND(J8>0,Assumptions!$B$2>F8),Assumptions!$B$2-F8,0) -> 0 | L8: =IF(J8<=0,"Paid",IF(K8=0,"Not due",IF(K8<=30,"1-30",IF(K8<=60,"31-60",IF(K8<=90,"61-90","90+"))))) -> Paid | M8: =IF(AND(J8<=0,I8<>""),I8-D8,"") -> 50
A9: INV-20250008 | B9: C005 | C9: =INDEX(Customers!$B$2:$B$11,MATCH(B9,Customers!$A$2:$A$11,0)) -> BlueWave Telecom | D9: 45854 | E9: =INDEX(Customers!$D$2:$D$11,MATCH(B9,Customers!$A$2:$A$11,0)) -> 45 | F9: =D9+E9 -> 45899 | G9: 16240 | H9: 16240 | I9: 45901 | J9: =G9-H9 -> 0 | K9: =IF(AND(J9>0,Assumptions!$B$2>F9),Assumptions!$B$2-F9,0) -> 0 | L9: =IF(J9<=0,"Paid",IF(K9=0,"Not due",IF(K9<=30,"1-30",IF(K9<=60,"31-60",IF(K9<=90,"61-90","90+"))))) -> Paid | M9: =IF(AND(J9<=0,I9<>""),I9-D9,"") -> 47
A10: INV-20250009 | B10: C010 | C10: =INDEX(Customers!$B$2:$B$11,MATCH(B10,Customers!$A$2:$A$11,0)) -> Oasis Retail Group | D10: 45857 | E10: =INDEX(Customers!$D$2:$D$11,MATCH(B10,Customers!$A$2:$A$11,0)) -> 30 | F10: =D10+E10 -> 45887 | G10: 35180 | H10: 35180 | I10: 45887 | J10: =G10-H10 -> 0 | K10: =IF(AND(J10>0,Assumptions!$B$2>F10),Assumptions!$B$2-F10,0) -> 0 | L10: =IF(J10<=0,"Paid",IF(K10=0,"Not due",IF(K10<=30,"1-30",IF(K10<=60,"31-60",IF(K10<=90,"61-90","90+"))))) -> Paid | M10: =IF(AND(J10<=0,I10<>""),I10-D10,"") -> 30
A11: INV-20250010 | B11: C004 | C11: =INDEX(Customers!$B$2:$B$11,MATCH(B11,Customers!$A$2:$A$11,0)) -> Desert Logistics | D11: 45860 | E11: =INDEX(Customers!$D$2:$D$11,MATCH(B11,Customers!$A$2:$A$11,0)) -> 30 | F11: =D11+E11 -> 45890 | G11: 11810 | H11: 11810 | I11: 45901 | J11: =G11-H11 -> 0 | K11: =IF(AND(J11>0,Assumptions!$B$2>F11),Assumptions!$B$2-F11,0) -> 0 | L11: =IF(J11<=0,"Paid",IF(K11=0,"Not due",IF(K11<=30,"1-30",IF(K11<=60,"31-60",IF(K11<=90,"61-90","90+"))))) -> Paid | M11: =IF(AND(J11<=0,I11<>""),I11-D11,"") -> 41
A12: INV-20250011 | B12: C007 | C12: =INDEX(Customers!$B$2:$B$11,MATCH(B12,Customers!$A$2:$A$11,0)) -> Sunrise Facilities | D12: 45863 | E12: =INDEX(Customers!$D$2:$D$11,MATCH(B12,Customers!$A$2:$A$11,0)) -> 30 | F12: =D12+E12 -> 45893 | G12: 6070 | H12: 3640 | I12: 45888 | J12: =G12-H12 -> 2430 | K12: =IF(AND(J12>0,Assumptions!$B$2>F12),Assumptions!$B$2-F12,0) -> 129 | L12: =IF(J12<=0,"Paid",IF(K12=0,"Not due",IF(K12<=30,"1-30",IF(K12<=60,"31-60",IF(K12<=90,"61-90","90+"))))) -> 90+ | M12: =IF(AND(J12<=0,I12<>""),I12-D12,"")
A13: INV-20250012 | B13: C001 | C13: =INDEX(Customers!$B$2:$B$11,MATCH(B13,Customers!$A$2:$A$11,0)) -> Al Noor Construction | D13: 45863 | E13: =INDEX(Customers!$D$2:$D$11,MATCH(B13,Customers!$A$2:$A$11,0)) -> 30 | F13: =D13+E13 -> 45893 | G13: 43490 | H13: 21740 | I13: 45888 | J13: =G13-H13 -> 21750 | K13: =IF(AND(J13>0,Assumptions!$B$2>F13),Assumptions!$B$2-F13,0) -> 129 | L13: =IF(J13<=0,"Paid",IF(K13=0,"Not due",IF(K13<=30,"1-30",IF(K13<=60,"31-60",IF(K13<=90,"61-90","90+"))))) -> 90+ | M13: =IF(AND(J13<=0,I13<>""),I13-D13,"")
... A25: INV-20250024 | B25: C009 | C25: =INDEX(Customers!$B$2:$B$11,MATCH(B25,Customers!$A$2:$A$11,0)) -> Prime Events | D25: 45893 | E25: =INDEX(Customers!$D$2:$D$11,MATCH(B25,Customers!$A$2:$A$11,0)) -> 15 | F25: =D25+E25 -> 45908 | G25: 10370 | H25: 5180 | I25: 45906 | J25: =G25-H25 -> 5190 | K25: =IF(AND(J25>0,Assumptions!$B$2>F25),Assumptions!$B$2-F25,0) -> 114 | L25: =IF(J25<=0,"Paid",IF(K25=0,"Not due",IF(K25<=30,"1-30",IF(K25<=60,"31-60",IF(K25<=90,"61-90","90+"))))) -> 90+ | M25: =IF(AND(J25<=0,I25<>""),I25-D25,"")
A26: INV-20250025 | B26: C008 | C26: =INDEX(Customers!$B$2:$B$11,MATCH(B26,Customers!$A$2:$A$11,0)) -> Coastal Roads Authority | D26: 45893 | E26: =INDEX(Customers!$D$2:$D$11,MATCH(B26,Customers!$A$2:$A$11,0)) -> 90 | F26: =D26+E26 -> 45983 | G26: 26490 | H26: 0 | J26: =G26-H26 -> 26490 | K26: =IF(AND(J26>0,Assumptions!$B$2>F26),Assumptions!$B$2-F26,0) -> 39 | L26: =IF(J26<=0,"Paid",IF(K26=0,"Not due",IF(K26<=30,"1-30",IF(K26<=60,"31-60",IF(K26<=90,"61-90","90+"))))) -> 31-60 | M26: =IF(AND(J26<=0,I26<>""),I26-D26,"")
A27: INV-20250026 | B27: C004 | C27: =INDEX(Customers!$B$2:$B$11,MATCH(B27,Customers!$A$2:$A$11,0)) -> Desert Logistics | D27: 45896 | E27: =INDEX(Customers!$D$2:$D$11,MATCH(B27,Customers!$A$2:$A$11,0)) -> 30 | F27: =D27+E27 -> 45926 | G27: 41530 | H27: 24920 | I27: 45921 | J27: =G27-H27 -> 16610 | K27: =IF(AND(J27>0,Assumptions!$B$2>F27),Assumptions!$B$2-F27,0) -> 96 | L27: =IF(J27<=0,"Paid",IF(K27=0,"Not due",IF(K27<=30,"1-30",IF(K27<=60,"31-60",IF(K27<=90,"61-90","90+"))))) -> 90+ | M27: =IF(AND(J27<=0,I27<>""),I27-D27,"")
A28: INV-20250027 | B28: C007 | C28: =INDEX(Customers!$B$2:$B$11,MATCH(B28,Customers!$A$2:$A$11,0)) -> Sunrise Facilities | D28: 45896 | E28: =INDEX(Customers!$D$2:$D$11,MATCH(B28,Customers!$A$2:$A$11,0)) -> 30 | F28: =D28+E28 -> 45926 | G28: 21720 | H28: 21720 | I28: 45930 | J28: =G28-H28 -> 0 | K28: =IF(AND(J28>0,Assumptions!$B$2>F28),Assumptions!$B$2-F28,0) -> 0 | L28: =IF(J28<=0,"Paid",IF(K28=0,"Not due",IF(K28<=30,"1-30",IF(K28<=60,"31-60",IF(K28<=90,"61-90","90+"))))) -> Paid | M28: =IF(AND(J28<=0,I28<>""),I28-D28,"") -> 34
A29: INV-20250028 | B29: C002 | C29: =INDEX(Customers!$B$2:$B$11,MATCH(B29,Customers!$A$2:$A$11,0)) -> Gulf Infra Projects | D29: 45899 | E29: =INDEX(Customers!$D$2:$D$11,MATCH(B29,Customers!$A$2:$A$11,0)) -> 45 | F29: =D29+E29 -> 45944 | G29: 18210 | H29: 18210 | I29: 45960 | J29: =G29-H29 -> 0 | K29: =IF(AND(J29>0,Assumptions!$B$2>F29),Assumptions!$B$2-F29,0) -> 0 | L29: =IF(J29<=0,"Paid",IF(K29=0,"Not due",IF(K29<=30,"1-30",IF(K29<=60,"31-60",IF(K29<=90,"61-90","90+"))))) -> Paid | M29: =IF(AND(J29<=0,I29<>""),I29-D29,"") -> 61
A30: INV-20250029 | B30: C010 | C30: =INDEX(Customers!$B$2:$B$11,MATCH(B30,Customers!$A$2:$A$11,0)) -> Oasis Retail Group | D30: 45902 | E30: =INDEX(Customers!$D$2:$D$11,MATCH(B30,Customers!$A$2:$A$11,0)) -> 30 | F30: =D30+E30 -> 45932 | G30: 4470 | H30: 4470 | I30: 45961 | J30: =G30-H30 -> 0 | K30: =IF(AND(J30>0,Assumptions!$B$2>F30),Assumptions!$B$2-F30,0) -> 0 | L30: =IF(J30<=0,"Paid",IF(K30=0,"Not due",IF(K30<=30,"1-30",IF(K30<=60,"31-60",IF(K30<=90,"61-90","90+"))))) -> Paid | M30: =IF(AND(J30<=0,I30<>""),I30-D30,"") -> 59
A31: INV-20250030 | B31: C010 | C31: =INDEX(Customers!$B$2:$B$11,MATCH(B31,Customers!$A$2:$A$11,0)) -> Oasis Retail Group | D31: 45905 | E31: =INDEX(Customers!$D$2:$D$11,MATCH(B31,Customers!$A$2:$A$11,0)) -> 30 | F31: =D31+E31 -> 45935 | G31: 29720 | H31: 29720 | I31: 45948 | J31: =G31-H31 -> 0 | K31: =IF(AND(J31>0,Assumptions!$B$2>F31),Assumptions!$B$2-F31,0) -> 0 | L31: =IF(J31<=0,"Paid",IF(K31=0,"Not due",IF(K31<=30,"1-30",IF(K31<=60,"31-60",IF(K31<=90,"61-90","90+"))))) -> Paid | M31: =IF(AND(J31<=0,I31<>""),I31-D31,"") -> 43
A32: INV-20250031 | B32: C003 | C32: =INDEX(Customers!$B$2:$B$11,MATCH(B32,Customers!$A$2:$A$11,0)) -> Metro Utilities Co | D32: 45908 | E32: =INDEX(Customers!$D$2:$D$11,MATCH(B32,Customers!$A$2:$A$11,0)) -> 60 | F32: =D32+E32 -> 45968 | G32: 44970 | H32: 44970 | I32: 46001 | J32: =G32-H32 -> 0 | K32: =IF(AND(J32>0,Assumptions!$B$2>F32),Assumptions!$B$2-F32,0) -> 0 | L32: =IF(J32<=0,"Paid",IF(K32=0,"Not due",IF(K32<=30,"1-30",IF(K32<=60,"31-60",IF(K32<=90,"61-90","90+"))))) -> Paid | M32: =IF(AND(J32<=0,I32<>""),I32-D32,"") -> 93
A33: INV-20250032 | B33: C003 | C33: =INDEX(Customers!$B$2:$B$11,MATCH(B33,Customers!$A$2:$A$11,0)) -> Metro Utilities Co | D33: 45908 | E33: =INDEX(Customers!$D$2:$D$11,MATCH(B33,Customers!$A$2:$A$11,0)) -> 60 | F33: =D33+E33 -> 45968 | G33: 36320 | H33: 0 | J33: =G33-H33 -> 36320 | K33: =IF(AND(J33>0,Assumptions!$B$2>F33),Assumptions!$B$2-F33,0) -> 54 | L33: =IF(J33<=0,"Paid",IF(K33=0,"Not due",IF(K33<=30,"1-30",IF(K33<=60,"31-60",IF(K33<=90,"61-90","90+"))))) -> 31-60 | M33: =IF(AND(J33<=0,I33<>""),I33-D33,"")
A34: INV-20250033 | B34: C002 | C34: =INDEX(Customers!$B$2:$B$11,MATCH(B34,Customers!$A$2:$A$11,0)) -> Gulf Infra Projects | D34: 45911 | E34: =INDEX(Customers!$D$2:$D$11,MATCH(B34,Customers!$A$2:$A$11,0)) -> 45 | F34: =D34+E34 -> 45956 | G34: 31780 | H34: 31780 | I34: 45984 | J34: =G34-H34 -> 0 | K34: =IF(AND(J34>0,Assumptions!$B$2>F34),Assumptions!$B$2-F34,0) -> 0 | L34: =IF(J34<=0,"Paid",IF(K34=0,"Not due",IF(K34<=30,"1-30",IF(K34<=60,"31-60",IF(K34<=90,"61-90","90+"))))) -> Paid | M34: =IF(AND(J34<=0,I34<>""),I34-D34,"") -> 73
A35: INV-20250034 | B35: C008 | C35: =INDEX(Customers!$B$2:$B$11,MATCH(B35,Customers!$A$2:$A$11,0)) -> Coastal Roads Authority | D35: 45911 | E35: =INDEX(Customers!$D$2:$D$11,MATCH(B35,Customers!$A$2:$A$11,0)) -> 90 | F35: =D35+E35 -> 46001 | G35: 27060 | H35: 0 | J35: =G35-H35 -> 27060 | K35: =IF(AND(J35>0,Assumptions!$B$2>F35),Assumptions!$B$2-F35,0) -> 21 | L35: =IF(J35<=0,"Paid",IF(K35=0,"Not due",IF(K35<=30,"1-30",IF(K35<=60,"31-60",IF(K35<=90,"61-90","90+"))))) -> 1-30 | M35: =IF(AND(J35<=0,I35<>""),I35-D35,"")
A36: INV-20250035 | B36: C007 | C36: =INDEX(Customers!$B$2:$B$11,MATCH(B36,Customers!$A$2:$A$11,0)) -> Sunrise Facilities | D36: 45914 | E36: =INDEX(Customers!$D$2:$D$11,MATCH(B36,Customers!$A$2:$A$11,0)) -> 30 | F36: =D36+E36 -> 45944 | G36: 27470 | H36: 27470 | I36: 45942 | J36: =G36-H36 -> 0 | K36: =IF(AND(J36>0,Assumptions!$B$2>F36),Assumptions!$B$2-F36,0) -> 0 | L36: =IF(J36<=0,"Paid",IF(K36=0,"Not due",IF(K36<=30,"1-30",IF(K36<=60,"31-60",IF(K36<=90,"61-90","90+"))))) -> Paid | M36: =IF(AND(J36<=0,I36<>""),I36-D36,"") -> 28
A37: INV-20250036 | B37: C007 | C37: =INDEX(Customers!$B$2:$B$11,MATCH(B37,Customers!$A$2:$A$11,0)) -> Sunrise Facilities | D37: 45914 | E37: =INDEX(Customers!$D$2:$D$11,MATCH(B37,Customers!$A$2:$A$11,0)) -> 30 | F37: =D37+E37 -> 45944 | G37: 33580 | H37: 33580 | I37: 45942 | J37: =G37-H37 -> 0 | K37: =IF(AND(J37>0,Assumptions!$B$2>F37),Assumptions!$B$2-F37,0) -> 0 | L37: =IF(J37<=0,"Paid",IF(K37=0,"Not due",IF(K37<=30,"1-30",IF(K37<=60,"31-60",IF(K37<=90,"61-90","90+"))))) -> Paid | M37: =IF(AND(J37<=0,I37<>""),I37-D37,"") -> 28
A38: INV-20250037 | B38: C008 | C38: =INDEX(Customers!$B$2:$B$11,MATCH(B38,Customers!$A$2:$A$11,0)) -> Coastal Roads Authority | D38: 45917 | E38: =INDEX(Customers!$D$2:$D$11,MATCH(B38,Customers!$A$2:$A$11,0)) -> 90 | F38: =D38+E38 -> 46007 | G38: 22430 | H38: 0 | J38: =G38-H38 -> 22430 | K38: =IF(AND(J38>0,Assumptions!$B$2>F38),Assumptions!$B$2-F38,0) -> 15 | L38: =IF(J38<=0,"Paid",IF(K38=0,"Not due",IF(K38<=30,"1-30",IF(K38<=60,"31-60",IF(K38<=90,"61-90","90+"))))) -> 1-30 | M38: =IF(AND(J38<=0,I38<>""),I38-D38,"")
A39: INV-20250038 | B39: C009 | C39: =INDEX(Customers!$B$2:$B$11,MATCH(B39,Customers!$A$2:$A$11,0)) -> Prime Events | D39: 45917 | E39: =INDEX(Customers!$D$2:$D$11,MATCH(B39,Customers!$A$2:$A$11,0)) -> 15 | F39: =D39+E39 -> 45932 | G39: 4250 | H39: 4250 | I39: 45932 | J39: =G39-H39 -> 0 | K39: =IF(AND(J39>0,Assumptions!$B$2>F39),Assumptions!$B$2-F39,0) -> 0 | L39: =IF(J39<=0,"Paid",IF(K39=0,"Not due",IF(K39<=30,"1-30",IF(K39<=60,"31-60",IF(K39<=90,"61-90","90+"))))) -> Paid | M39: =IF(AND(J39<=0,I39<>""),I39-D39,"") -> 15
A40: INV-20250039 | B40: C002 | C40: =INDEX(Customers!$B$2:$B$11,MATCH(B40,Customers!$A$2:$A$11,0)) -> Gulf Infra Projects | D40: 45920 | E40: =INDEX(Customers!$D$2:$D$11,MATCH(B40,Customers!$A$2:$A$11,0)) -> 45 | F40: =D40+E40 -> 45965 | G40: 23880 | H40: 14330 | I40: 45966 | J40: =G40-H40 -> 9550 | K40: =IF(AND(J40>0,Assumptions!$B$2>F40),Assumptions!$B$2-F40,0) -> 57 | L40: =IF(J40<=0,"Paid",IF(K40=0,"Not due",IF(K40<=30,"1-30",IF(K40<=60,"31-60",IF(K40<=90,"61-90","90+"))))) -> 31-60 | M40: =IF(AND(J40<=0,I40<>""),I40-D40,"")
A41: INV-20250040 | B41: C010 | C41: =INDEX(Customers!$B$2:$B$11,MATCH(B41,Customers!$A$2:$A$11,0)) -> Oasis Retail Group | D41: 45923 | E41: =INDEX(Customers!$D$2:$D$11,MATCH(B41,Customers!$A$2:$A$11,0)) -> 30 | F41: =D41+E41 -> 45953 | G41: 11510 | H41: 11510 | I41: 45953 | J41: =G41-H41 -> 0 | K41: =IF(AND(J41>0,Assumptions!$B$2>F41),Assumptions!$B$2-F41,0) -> 0 | L41: =IF(J41<=0,"Paid",IF(K41=0,"Not due",IF(K41<=30,"1-30",IF(K41<=60,"31-60",IF(K41<=90,"61-90","90+"))))) -> Paid | M41: =IF(AND(J41<=0,I41<>""),I41-D41,"") -> 30
A42: INV-20250041 | B42: C008 | C42: =INDEX(Customers!$B$2:$B$11,MATCH(B42,Customers!$A$2:$A$11,0)) -> Coastal Roads Authority | D42: 45926 | E42: =INDEX(Customers!$D$2:$D$11,MATCH(B42,Customers!$A$2:$A$11,0)) -> 90 | F42: =D42+E42 -> 46016 | G42: 40450 | H42: 0 | J42: =G42-H42 -> 40450 | K42: =IF(AND(J42>0,Assumptions!$B$2>F42),Assumptions!$B$2-F42,0) -> 6 | L42: =IF(J42<=0,"Paid",IF(K42=0,"Not due",IF(K42<=30,"1-30",IF(K42<=60,"31-60",IF(K42<=90,"61-90","90+"))))) -> 1-30 | M42: =IF(AND(J42<=0,I42<>""),I42-D42,"")
A43: INV-20250042 | B43: C004 | C43: =INDEX(Customers!$B$2:$B$11,MATCH(B43,Customers!$A$2:$A$11,0)) -> Desert Logistics | D43: 45926 | E43: =INDEX(Customers!$D$2:$D$11,MATCH(B43,Customers!$A$2:$A$11,0)) -> 30 | F43: =D43+E43 -> 45956 | G43: 29640 | H43: 29640 | I43: 45968 | J43: =G43-H43 -> 0 | K43: =IF(AND(J43>0,Assumptions!$B$2>F43),Assumptions!$B$2-F43,0) -> 0 | L43: =IF(J43<=0,"Paid",IF(K43=0,"Not due",IF(K43<=30,"1-30",IF(K43<=60,"31-60",IF(K43<=90,"61-90","90+"))))) -> Paid | M43: =IF(AND(J43<=0,I43<>""),I43-D43,"") -> 42
A44: INV-20250043 | B44: C004 | C44: =INDEX(Customers!$B$2:$B$11,MATCH(B44,Customers!$A$2:$A$11,0)) -> Desert Logistics | D44: 45929 | E44: =INDEX(Customers!$D$2:$D$11,MATCH(B44,Customers!$A$2:$A$11,0)) -> 30 | F44: =D44+E44 -> 45959 | G44: 19150 | H44: 19150 | I44: 45955 | J44: =G44-H44 -> 0 | K44: =IF(AND(J44>0,Assumptions!$B$2>F44),Assumptions!$B$2-F44,0) -> 0 | L44: =IF(J44<=0,"Paid",IF(K44=0,"Not due",IF(K44<=30,"1-30",IF(K44<=60,"31-60",IF(K44<=90,"61-90","90+"))))) -> Paid | M44: =IF(AND(J44<=0,I44<>""),I44-D44,"") -> 26
A45: INV-20250044 | B45: C002 | C45: =INDEX(Customers!$B$2:$B$11,MATCH(B45,Customers!$A$2:$A$11,0)) -> Gulf Infra Projects | D45: 45932 | E45: =INDEX(Customers!$D$2:$D$11,MATCH(B45,Customers!$A$2:$A$11,0)) -> 45 | F45: =D45+E45 -> 45977 | G45: 42900 | H45: 42900 | I45: 45988 | J45: =G45-H45 -> 0 | K45: =IF(AND(J45>0,Assumptions!$B$2>F45),Assumptions!$B$2-F45,0) -> 0 | L45: =IF(J45<=0,"Paid",IF(K45=0,"Not due",IF(K45<=30,"1-30",IF(K45<=60,"31-60",IF(K45<=90,"61-90","90+"))))) -> Paid | M45: =IF(AND(J45<=0,I45<>""),I45-D45,"") -> 56
A46: INV-20250045 | B46: C008 | C46: =INDEX(Customers!$B$2:$B$11,MATCH(B46,Customers!$A$2:$A$11,0)) -> Coastal Roads Authority | D46: 45935 | E46: =INDEX(Customers!$D$2:$D$11,MATCH(B46,Customers!$A$2:$A$11,0)) -> 90 | F46: =D46+E46 -> 46025 | G46: 14560 | H46: 0 | J46: =G46-H46 -> 14560 | K46: =IF(AND(J46>0,Assumptions!$B$2>F46),Assumptions!$B$2-F46,0) -> 0 | L46: =IF(J46<=0,"Paid",IF(K46=0,"Not due",IF(K46<=30,"1-30",IF(K46<=60,"31-60",IF(K46<=90,"61-90","90+"))))) -> Not due | M46: =IF(AND(J46<=0,I46<>""),I46-D46,"")
A47: INV-20250046 | B47: C009 | C47: =INDEX(Customers!$B$2:$B$11,MATCH(B47,Customers!$A$2:$A$11,0)) -> Prime Events | D47: 45935 | E47: =INDEX(Customers!$D$2:$D$11,MATCH(B47,Customers!$A$2:$A$11,0)) -> 15 | F47: =D47+E47 -> 45950 | G47: 23740 | H47: 23740 | I47: 45961 | J47: =G47-H47 -> 0 | K47: =IF(AND(J47>0,Assumptions!$B$2>F47),Assumptions!$B$2-F47,0) -> 0 | L47: =IF(J47<=0,"Paid",IF(K47=0,"Not due",IF(K47<=30,"1-30",IF(K47<=60,"31-60",IF(K47<=90,"61-90","90+"))))) -> Paid | M47: =IF(AND(J47<=0,I47<>""),I47-D47,"") -> 26
A48: INV-20250047 | B48: C006 | C48: =INDEX(Customers!$B$2:$B$11,MATCH(B48,Customers!$A$2:$A$11,0)) -> Harbor Developers | D48: 45938 | E48: =INDEX(Customers!$D$2:$D$11,MATCH(B48,Customers!$A$2:$A$11,0)) -> 60 | F48: =D48+E48 -> 45998 | G48: 6140 | H48: 0 | J48: =G48-H48 -> 6140 | K48: =IF(AND(J48>0,Assumptions!$B$2>F48),Assumptions!$B$2-F48,0) -> 24 | L48: =IF(J48<=0,"Paid",IF(K48=0,"Not due",IF(K48<=30,"1-30",IF(K48<=60,"31-60",IF(K48<=90,"61-90","90+"))))) -> 1-30 | M48: =IF(AND(J48<=0,I48<>""),I48-D48,"")
A49: INV-20250048 | B49: C001 | C49: =INDEX(Customers!$B$2:$B$11,MATCH(B49,Customers!$A$2:$A$11,0)) -> Al Noor Construction | D49: 45938 | E49: =INDEX(Customers!$D$2:$D$11,MATCH(B49,Customers!$A$2:$A$11,0)) -> 30 | F49: =D49+E49 -> 45968 | G49: 31490 | H49: 31490 | I49: 45976 | J49: =G49-H49 -> 0 | K49: =IF(AND(J49>0,Assumptions!$B$2>F49),Assumptions!$B$2-F49,0) -> 0 | L49: =IF(J49<=0,"Paid",IF(K49=0,"Not due",IF(K49<=30,"1-30",IF(K49<=60,"31-60",IF(K49<=90,"61-90","90+"))))) -> Paid | M49: =IF(AND(J49<=0,I49<>""),I49-D49,"") -> 38
A50: INV-20250049 | B50: C003 | C50: =INDEX(Customers!$B$2:$B$11,MATCH(B50,Customers!$A$2:$A$11,0)) -> Metro Utilities Co | D50: 45941 | E50: =INDEX(Customers!$D$2:$D$11,MATCH(B50,Customers!$A$2:$A$11,0)) -> 60 | F50: =D50+E50 -> 46001 | G50: 20020 | H50: 0 | J50: =G50-H50 -> 20020 | K50: =IF(AND(J50>0,Assumptions!$B$2>F50),Assumptions!$B$2-F50,0) -> 21 | L50: =IF(J50<=0,"Paid",IF(K50=0,"Not due",IF(K50<=30,"1-30",IF(K50<=60,"31-60",IF(K50<=90,"61-90","90+"))))) -> 1-30 | M50: =IF(AND(J50<=0,I50<>""),I50-D50,"")
A51: INV-20250050 | B51: C004 | C51: =INDEX(Customers!$B$2:$B$11,MATCH(B51,Customers!$A$2:$A$11,0)) -> Desert Logistics | D51: 45944 | E51: =INDEX(Customers!$D$2:$D$11,MATCH(B51,Customers!$A$2:$A$11,0)) -> 30 | F51: =D51+E51 -> 45974 | G51: 35730 | H51: 35730 | I51: 45988 | J51: =G51-H51 -> 0 | K51: =IF(AND(J51>0,Assumptions!$B$2>F51),Assumptions!$B$2-F51,0) -> 0 | L51: =IF(J51<=0,"Paid",IF(K51=0,"Not due",IF(K51<=30,"1-30",IF(K51<=60,"31-60",IF(K51<=90,"61-90","90+"))))) -> Paid | M51: =IF(AND(J51<=0,I51<>""),I51-D51,"") -> 44
A52: INV-20250051 | B52: C002 | C52: =INDEX(Customers!$B$2:$B$11,MATCH(B52,Customers!$A$2:$A$11,0)) -> Gulf Infra Projects | D52: 45944 | E52: =INDEX(Customers!$D$2:$D$11,MATCH(B52,Customers!$A$2:$A$11,0)) -> 45 | F52: =D52+E52 -> 45989 | G52: 21750 | H52: 21750 | I52: 45996 | J52: =G52-H52 -> 0 | K52: =IF(AND(J52>0,Assumptions!$B$2>F52),Assumptions!$B$2-F52,0) -> 0 | L52: =IF(J52<=0,"Paid",IF(K52=0,"Not due",IF(K52<=30,"1-30",IF(K52<=60,"31-60",IF(K52<=90,"61-90","90+"))))) -> Paid | M52: =IF(AND(J52<=0,I52<>""),I52-D52,"") -> 52
A53: INV-20250052 | B53: C004 | C53: =INDEX(Customers!$B$2:$B$11,MATCH(B53,Customers!$A$2:$A$11,0)) -> Desert Logistics | D53: 45947 | E53: =INDEX(Customers!$D$2:$D$11,MATCH(B53,Customers!$A$2:$A$11,0)) -> 30 | F53: =D53+E53 -> 45977 | G53: 37600 | H53: 37600 | I53: 45972 | J53: =G53-H53 -> 0 | K53: =IF(AND(J53>0,Assumptions!$B$2>F53),Assumptions!$B$2-F53,0) -> 0 | L53: =IF(J53<=0,"Paid",IF(K53=0,"Not due",IF(K53<=30,"1-30",IF(K53<=60,"31-60",IF(K53<=90,"61-90","90+"))))) -> Paid | M53: =IF(AND(J53<=0,I53<>""),I53-D53,"") -> 25
A54: INV-20250053 | B54: C009 | C54: =INDEX(Customers!$B$2:$B$11,MATCH(B54,Customers!$A$2:$A$11,0)) -> Prime Events | D54: 45950 | E54: =INDEX(Customers!$D$2:$D$11,MATCH(B54,Customers!$A$2:$A$11,0)) -> 15 | F54: =D54+E54 -> 45965 | G54: 33000 | H54: 33000 | I54: 45970 | J54: =G54-H54 -> 0 | K54: =IF(AND(J54>0,Assumptions!$B$2>F54),Assumptions!$B$2-F54,0) -> 0 | L54: =IF(J54<=0,"Paid",IF(K54=0,"Not due",IF(K54<=30,"1-30",IF(K54<=60,"31-60",IF(K54<=90,"61-90","90+"))))) -> Paid | M54: =IF(AND(J54<=0,I54<>""),I54-D54,"") -> 20
A55: INV-20250054 | B55: C009 | C55: =INDEX(Customers!$B$2:$B$11,MATCH(B55,Customers!$A$2:$A$11,0)) -> Prime Events | D55: 45950 | E55: =INDEX(Customers!$D$2:$D$11,MATCH(B55,Customers!$A$2:$A$11,0)) -> 15 | F55: =D55+E55 -> 45965 | G55: 24020 | H55: 24020 | I55: 45973 | J55: =G55-H55 -> 0 | K55: =IF(AND(J55>0,Assumptions!$B$2>F55),Assumptions!$B$2-F55,0) -> 0 | L55: =IF(J55<=0,"Paid",IF(K55=0,"Not due",IF(K55<=30,"1-30",IF(K55<=60,"31-60",IF(K55<=90,"61-90","90+"))))) -> Paid | M55: =IF(AND(J55<=0,I55<>""),I55-D55,"") -> 23
A56: INV-20250055 | B56: C002 | C56: =INDEX(Customers!$B$2:$B$11,MATCH(B56,Customers!$A$2:$A$11,0)) -> Gulf Infra Projects | D56: 45953 | E56: =INDEX(Customers!$D$2:$D$11,MATCH(B56,Customers!$A$2:$A$11,0)) -> 45 | F56: =D56+E56 -> 45998 | G56: 20240 | H56: 20240 | I56: 46019 | J56: =G56-H56 -> 0 | K56: =IF(AND(J56>0,Assumptions!$B$2>F56),Assumptions!$B$2-F56,0) -> 0 | L56: =IF(J56<=0,"Paid",IF(K56=0,"Not due",IF(K56<=30,"1-30",IF(K56<=60,"31-60",IF(K56<=90,"61-90","90+"))))) -> Paid | M56: =IF(AND(J56<=0,I56<>""),I56-D56,"") -> 66
A57: INV-20250056 | B57: C007 | C57: =INDEX(Customers!$B$2:$B$11,MATCH(B57,Customers!$A$2:$A$11,0)) -> Sunrise Facilities | D57: 45956 | E57: =INDEX(Customers!$D$2:$D$11,MATCH(B57,Customers!$A$2:$A$11,0)) -> 30 | F57: =D57+E57 -> 45986 | G57: 26100 | H57: 26100 | I57: 45982 | J57: =G57-H57 -> 0 | K57: =IF(AND(J57>0,Assumptions!$B$2>F57),Assumptions!$B$2-F57,0) -> 0 | L57: =IF(J57<=0,"Paid",IF(K57=0,"Not due",IF(K57<=30,"1-30",IF(K57<=60,"31-60",IF(K57<=90,"61-90","90+"))))) -> Paid | M57: =IF(AND(J57<=0,I57<>""),I57-D57,"") -> 26
A58: INV-20250057 | B58: C008 | C58: =INDEX(Customers!$B$2:$B$11,MATCH(B58,Customers!$A$2:$A$11,0)) -> Coastal Roads Authority | D58: 45959 | E58: =INDEX(Customers!$D$2:$D$11,MATCH(B58,Customers!$A$2:$A$11,0)) -> 90 | F58: =D58+E58 -> 46049 | G58: 16710 | H58: 0 | J58: =G58-H58 -> 16710 | K58: =IF(AND(J58>0,Assumptions!$B$2>F58),Assumptions!$B$2-F58,0) -> 0 | L58: =IF(J58<=0,"Paid",IF(K58=0,"Not due",IF(K58<=30,"1-30",IF(K58<=60,"31-60",IF(K58<=90,"61-90","90+"))))) -> Not due | M58: =IF(AND(J58<=0,I58<>""),I58-D58,"")
A59: INV-20250058 | B59: C002 | C59: =INDEX(Customers!$B$2:$B$11,MATCH(B59,Customers!$A$2:$A$11,0)) -> Gulf Infra Projects | D59: 45959 | E59: =INDEX(Customers!$D$2:$D$11,MATCH(B59,Customers!$A$2:$A$11,0)) -> 45 | F59: =D59+E59 -> 46004 | G59: 11960 | H59: 11960 | I59: 46018 | J59: =G59-H59 -> 0 | K59: =IF(AND(J59>0,Assumptions!$B$2>F59),Assumptions!$B$2-F59,0) -> 0 | L59: =IF(J59<=0,"Paid",IF(K59=0,"Not due",IF(K59<=30,"1-30",IF(K59<=60,"31-60",IF(K59<=90,"61-90","90+"))))) -> Paid | M59: =IF(AND(J59<=0,I59<>""),I59-D59,"") -> 59
A60: INV-20250059 | B60: C009 | C60: =INDEX(Customers!$B$2:$B$11,MATCH(B60,Customers!$A$2:$A$11,0)) -> Prime Events | D60: 45962 | E60: =INDEX(Customers!$D$2:$D$11,MATCH(B60,Customers!$A$2:$A$11,0)) -> 15 | F60: =D60+E60 -> 45977 | G60: 44020 | H60: 33020 | I60: 45985 | J60: =G60-H60 -> 11000 | K60: =IF(AND(J60>0,Assumptions!$B$2>F60),Assumptions!$B$2-F60,0) -> 45 | L60: =IF(J60<=0,"Paid",IF(K60=0,"Not due",IF(K60<=30,"1-30",IF(K60<=60,"31-60",IF(K60<=90,"61-90","90+"))))) -> 31-60 | M60: =IF(AND(J60<=0,I60<>""),I60-D60,"")
A61: INV-20250060 | B61: C002 | C61: =INDEX(Customers!$B$2:$B$11,MATCH(B61,Customers!$A$2:$A$11,0)) -> Gulf Infra Projects | D61: 45962 | E61: =INDEX(Customers!$D$2:$D$11,MATCH(B61,Customers!$A$2:$A$11,0)) -> 45 | F61: =D61+E61 -> 46007 | G61: 4560 | H61: 4560 | I61: 46019 | J61: =G61-H61 -> 0 | K61: =IF(AND(J61>0,Assumptions!$B$2>F61),Assumptions!$B$2-F61,0) -> 0 | L61: =IF(J61<=0,"Paid",IF(K61=0,"Not due",IF(K61<=30,"1-30",IF(K61<=60,"31-60",IF(K61<=90,"61-90","90+"))))) -> Paid | M61: =IF(AND(J61<=0,I61<>""),I61-D61,"") -> 57
A62: INV-20250061 | B62: C008 | C62: =INDEX(Customers!$B$2:$B$11,MATCH(B62,Customers!$A$2:$A$11,0)) -> Coastal Roads Authority | D62: 45965 | E62: =INDEX(Customers!$D$2:$D$11,MATCH(B62,Customers!$A$2:$A$11,0)) -> 90 | F62: =D62+E62 -> 46055 | G62: 41630 | H62: 0 | J62: =G62-H62 -> 41630 | K62: =IF(AND(J62>0,Assumptions!$B$2>F62),Assumptions!$B$2-F62,0) -> 0 | L62: =IF(J62<=0,"Paid",IF(K62=0,"Not due",IF(K62<=30,"1-30",IF(K62<=60,"31-60",IF(K62<=90,"61-90","90+"))))) -> Not due | M62: =IF(AND(J62<=0,I62<>""),I62-D62,"")
A63: INV-20250062 | B63: C007 | C63: =INDEX(Customers!$B$2:$B$11,MATCH(B63,Customers!$A$2:$A$11,0)) -> Sunrise Facilities | D63: 45965 | E63: =INDEX(Customers!$D$2:$D$11,MATCH(B63,Customers!$A$2:$A$11,0)) -> 30 | F63: =D63+E63 -> 45995 | G63: 36590 | H63: 36590 | I63: 46010 | J63: =G63-H63 -> 0 | K63: =IF(AND(J63>0,Assumptions!$B$2>F63),Assumptions!$B$2-F63,0) -> 0 | L63: =IF(J63<=0,"Paid",IF(K63=0,"Not due",IF(K63<=30,"1-30",IF(K63<=60,"31-60",IF(K63<=90,"61-90","90+"))))) -> Paid | M63: =IF(AND(J63<=0,I63<>""),I63-D63,"") -> 45
A64: INV-20250063 | B64: C008 | C64: =INDEX(Customers!$B$2:$B$11,MATCH(B64,Customers!$A$2:$A$11,0)) -> Coastal Roads Authority | D64: 45968 | E64: =INDEX(Customers!$D$2:$D$11,MATCH(B64,Customers!$A$2:$A$11,0)) -> 90 | F64: =D64+E64 -> 46058 | G64: 9240 | H64: 0 | J64: =G64-H64 -> 9240 | K64: =IF(AND(J64>0,Assumptions!$B$2>F64),Assumptions!$B$2-F64,0) -> 0 | L64: =IF(J64<=0,"Paid",IF(K64=0,"Not due",IF(K64<=30,"1-30",IF(K64<=60,"31-60",IF(K64<=90,"61-90","90+"))))) -> Not due | M64: =IF(AND(J64<=0,I64<>""),I64-D64,"")
A65: INV-20250064 | B65: C008 | C65: =INDEX(Customers!$B$2:$B$11,MATCH(B65,Customers!$A$2:$A$11,0)) -> Coastal Roads Authority | D65: 45971 | E65: =INDEX(Customers!$D$2:$D$11,MATCH(B65,Customers!$A$2:$A$11,0)) -> 90 | F65: =D65+E65 -> 46061 | G65: 27320 | H65: 0 | J65: =G65-H65 -> 27320 | K65: =IF(AND(J65>0,Assumptions!$B$2>F65),Assumptions!$B$2-F65,0) -> 0 | L65: =IF(J65<=0,"Paid",IF(K65=0,"Not due",IF(K65<=30,"1-30",IF(K65<=60,"31-60",IF(K65<=90,"61-90","90+"))))) -> Not due | M65: =IF(AND(J65<=0,I65<>""),I65-D65,"")
A66: INV-20250065 | B66: C002 | C66: =INDEX(Customers!$B$2:$B$11,MATCH(B66,Customers!$A$2:$A$11,0)) -> Gulf Infra Projects | D66: 45971 | E66: =INDEX(Customers!$D$2:$D$11,MATCH(B66,Customers!$A$2:$A$11,0)) -> 45 | F66: =D66+E66 -> 46016 | G66: 34830 | H66: 34830 | I66: 46021 | J66: =G66-H66 -> 0 | K66: =IF(AND(J66>0,Assumptions!$B$2>F66),Assumptions!$B$2-F66,0) -> 0 | L66: =IF(J66<=0,"Paid",IF(K66=0,"Not due",IF(K66<=30,"1-30",IF(K66<=60,"31-60",IF(K66<=90,"61-90","90+"))))) -> Paid | M66: =IF(AND(J66<=0,I66<>""),I66-D66,"") -> 50
A67: INV-20250066 | B67: C009 | C67: =INDEX(Customers!$B$2:$B$11,MATCH(B67,Customers!$A$2:$A$11,0)) -> Prime Events | D67: 45974 | E67: =INDEX(Customers!$D$2:$D$11,MATCH(B67,Customers!$A$2:$A$11,0)) -> 15 | F67: =D67+E67 -> 45989 | G67: 24600 | H67: 24600 | I67: 45995 | J67: =G67-H67 -> 0 | K67: =IF(AND(J67>0,Assumptions!$B$2>F67),Assumptions!$B$2-F67,0) -> 0 | L67: =IF(J67<=0,"Paid",IF(K67=0,"Not due",IF(K67<=30,"1-30",IF(K67<=60,"31-60",IF(K67<=90,"61-90","90+"))))) -> Paid | M67: =IF(AND(J67<=0,I67<>""),I67-D67,"") -> 21
A68: INV-20250067 | B68: C010 | C68: =INDEX(Customers!$B$2:$B$11,MATCH(B68,Customers!$A$2:$A$11,0)) -> Oasis Retail Group | D68: 45977 | E68: =INDEX(Customers!$D$2:$D$11,MATCH(B68,Customers!$A$2:$A$11,0)) -> 30 | F68: =D68+E68 -> 46007 | G68: 11750 | H68: 0 | J68: =G68-H68 -> 11750 | K68: =IF(AND(J68>0,Assumptions!$B$2>F68),Assumptions!$B$2-F68,0) -> 15 | L68: =IF(J68<=0,"Paid",IF(K68=0,"Not due",IF(K68<=30,"1-30",IF(K68<=60,"31-60",IF(K68<=90,"61-90","90+"))))) -> 1-30 | M68: =IF(AND(J68<=0,I68<>""),I68-D68,"")
A69: INV-20250068 | B69: C009 | C69: =INDEX(Customers!$B$2:$B$11,MATCH(B69,Customers!$A$2:$A$11,0)) -> Prime Events | D69: 45977 | E69: =INDEX(Customers!$D$2:$D$11,MATCH(B69,Customers!$A$2:$A$11,0)) -> 15 | F69: =D69+E69 -> 45992 | G69: 14460 | H69: 14460 | I69: 45987 | J69: =G69-H69 -> 0 | K69: =IF(AND(J69>0,Assumptions!$B$2>F69),Assumptions!$B$2-F69,0) -> 0 | L69: =IF(J69<=0,"Paid",IF(K69=0,"Not due",IF(K69<=30,"1-30",IF(K69<=60,"31-60",IF(K69<=90,"61-90","90+"))))) -> Paid | M69: =IF(AND(J69<=0,I69<>""),I69-D69,"") -> 10
A70: INV-20250069 | B70: C009 | C70: =INDEX(Customers!$B$2:$B$11,MATCH(B70,Customers!$A$2:$A$11,0)) -> Prime Events | D70: 45980 | E70: =INDEX(Customers!$D$2:$D$11,MATCH(B70,Customers!$A$2:$A$11,0)) -> 15 | F70: =D70+E70 -> 45995 | G70: 3210 | H70: 3210 | I70: 45991 | J70: =G70-H70 -> 0 | K70: =IF(AND(J70>0,Assumptions!$B$2>F70),Assumptions!$B$2-F70,0) -> 0 | L70: =IF(J70<=0,"Paid",IF(K70=0,"Not due",IF(K70<=30,"1-30",IF(K70<=60,"31-60",IF(K70<=90,"61-90","90+"))))) -> Paid | M70: =IF(AND(J70<=0,I70<>""),I70-D70,"") -> 11
A71: INV-20250070 | B71: C008 | C71: =INDEX(Customers!$B$2:$B$11,MATCH(B71,Customers!$A$2:$A$11,0)) -> Coastal Roads Authority | D71: 45983 | E71: =INDEX(Customers!$D$2:$D$11,MATCH(B71,Customers!$A$2:$A$11,0)) -> 90 | F71: =D71+E71 -> 46073 | G71: 6920 | H71: 0 | J71: =G71-H71 -> 6920 | K71: =IF(AND(J71>0,Assumptions!$B$2>F71),Assumptions!$B$2-F71,0) -> 0 | L71: =IF(J71<=0,"Paid",IF(K71=0,"Not due",IF(K71<=30,"1-30",IF(K71<=60,"31-60",IF(K71<=90,"61-90","90+"))))) -> Not due | M71: =IF(AND(J71<=0,I71<>""),I71-D71,"")
A72: INV-20250071 | B72: C002 | C72: =INDEX(Customers!$B$2:$B$11,MATCH(B72,Customers!$A$2:$A$11,0)) -> Gulf Infra Projects | D72: 45986 | E72: =INDEX(Customers!$D$2:$D$11,MATCH(B72,Customers!$A$2:$A$11,0)) -> 45 | F72: =D72+E72 -> 46031 | G72: 42090 | H72: 0 | J72: =G72-H72 -> 42090 | K72: =IF(AND(J72>0,Assumptions!$B$2>F72),Assumptions!$B$2-F72,0) -> 0 | L72: =IF(J72<=0,"Paid",IF(K72=0,"Not due",IF(K72<=30,"1-30",IF(K72<=60,"31-60",IF(K72<=90,"61-90","90+"))))) -> Not due | M72: =IF(AND(J72<=0,I72<>""),I72-D72,"")
A73: INV-20250072 | B73: C005 | C73: =INDEX(Customers!$B$2:$B$11,MATCH(B73,Customers!$A$2:$A$11,0)) -> BlueWave Telecom | D73: 45989 | E73: =INDEX(Customers!$D$2:$D$11,MATCH(B73,Customers!$A$2:$A$11,0)) -> 45 | F73: =D73+E73 -> 46034 | G73: 13340 | H73: 0 | J73: =G73-H73 -> 13340 | K73: =IF(AND(J73>0,Assumptions!$B$2>F73),Assumptions!$B$2-F73,0) -> 0 | L73: =IF(J73<=0,"Paid",IF(K73=0,"Not due",IF(K73<=30,"1-30",IF(K73<=60,"31-60",IF(K73<=90,"61-90","90+"))))) -> Not due | M73: =IF(AND(J73<=0,I73<>""),I73-D73,"")
A74: INV-20250073 | B74: C008 | C74: =INDEX(Customers!$B$2:$B$11,MATCH(B74,Customers!$A$2:$A$11,0)) -> Coastal Roads Authority | D74: 45989 | E74: =INDEX(Customers!$D$2:$D$11,MATCH(B74,Customers!$A$2:$A$11,0)) -> 90 | F74: =D74+E74 -> 46079 | G74: 8330 | H74: 0 | J74: =G74-H74 -> 8330 | K74: =IF(AND(J74>0,Assumptions!$B$2>F74),Assumptions!$B$2-F74,0) -> 0 | L74: =IF(J74<=0,"Paid",IF(K74=0,"Not due",IF(K74<=30,"1-30",IF(K74<=60,"31-60",IF(K74<=90,"61-90","90+"))))) -> Not due | M74: =IF(AND(J74<=0,I74<>""),I74-D74,"")
A75: INV-20250074 | B75: C009 | C75: =INDEX(Customers!$B$2:$B$11,MATCH(B75,Customers!$A$2:$A$11,0)) -> Prime Events | D75: 45992 | E75: =INDEX(Customers!$D$2:$D$11,MATCH(B75,Customers!$A$2:$A$11,0)) -> 15 | F75: =D75+E75 -> 46007 | G75: 16320 | H75: 16320 | I75: 46015 | J75: =G75-H75 -> 0 | K75: =IF(AND(J75>0,Assumptions!$B$2>F75),Assumptions!$B$2-F75,0) -> 0 | L75: =IF(J75<=0,"Paid",IF(K75=0,"Not due",IF(K75<=30,"1-30",IF(K75<=60,"31-60",IF(K75<=90,"61-90","90+"))))) -> Paid | M75: =IF(AND(J75<=0,I75<>""),I75-D75,"") -> 23
A76: INV-20250075 | B76: C005 | C76: =INDEX(Customers!$B$2:$B$11,MATCH(B76,Customers!$A$2:$A$11,0)) -> BlueWave Telecom | D76: 45992 | E76: =INDEX(Customers!$D$2:$D$11,MATCH(B76,Customers!$A$2:$A$11,0)) -> 45 | F76: =D76+E76 -> 46037 | G76: 8440 | H76: 0 | J76: =G76-H76 -> 8440 | K76: =IF(AND(J76>0,Assumptions!$B$2>F76),Assumptions!$B$2-F76,0) -> 0 | L76: =IF(J76<=0,"Paid",IF(K76=0,"Not due",IF(K76<=30,"1-30",IF(K76<=60,"31-60",IF(K76<=90,"61-90","90+"))))) -> Not due | M76: =IF(AND(J76<=0,I76<>""),I76-D76,"")
A77: INV-20250076 | B77: C003 | C77: =INDEX(Customers!$B$2:$B$11,MATCH(B77,Customers!$A$2:$A$11,0)) -> Metro Utilities Co | D77: 45995 | E77: =INDEX(Customers!$D$2:$D$11,MATCH(B77,Customers!$A$2:$A$11,0)) -> 60 | F77: =D77+E77 -> 46055 | G77: 12540 | H77: 0 | J77: =G77-H77 -> 12540 | K77: =IF(AND(J77>0,Assumptions!$B$2>F77),Assumptions!$B$2-F77,0) -> 0 | L77: =IF(J77<=0,"Paid",IF(K77=0,"Not due",IF(K77<=30,"1-30",IF(K77<=60,"31-60",IF(K77<=90,"61-90","90+"))))) -> Not due | M77: =IF(AND(J77<=0,I77<>""),I77-D77,"")
A78: INV-20250077 | B78: C006 | C78: =INDEX(Customers!$B$2:$B$11,MATCH(B78,Customers!$A$2:$A$11,0)) -> Harbor Developers | D78: 45998 | E78: =INDEX(Customers!$D$2:$D$11,MATCH(B78,Customers!$A$2:$A$11,0)) -> 60 | F78: =D78+E78 -> 46058 | G78: 33390 | H78: 0 | J78: =G78-H78 -> 33390 | K78: =IF(AND(J78>0,Assumptions!$B$2>F78),Assumptions!$B$2-F78,0) -> 0 | L78: =IF(J78<=0,"Paid",IF(K78=0,"Not due",IF(K78<=30,"1-30",IF(K78<=60,"31-60",IF(K78<=90,"61-90","90+"))))) -> Not due | M78: =IF(AND(J78<=0,I78<>""),I78-D78,"")
A79: INV-20250078 | B79: C008 | C79: =INDEX(Customers!$B$2:$B$11,MATCH(B79,Customers!$A$2:$A$11,0)) -> Coastal Roads Authority | D79: 45998 | E79: =INDEX(Customers!$D$2:$D$11,MATCH(B79,Customers!$A$2:$A$11,0)) -> 90 | F79: =D79+E79 -> 46088 | G79: 33700 | H79: 0 | J79: =G79-H79 -> 33700 | K79: =IF(AND(J79>0,Assumptions!$B$2>F79),Assumptions!$B$2-F79,0) -> 0 | L79: =IF(J79<=0,"Paid",IF(K79=0,"Not due",IF(K79<=30,"1-30",IF(K79<=60,"31-60",IF(K79<=90,"61-90","90+"))))) -> Not due | M79: =IF(AND(J79<=0,I79<>""),I79-D79,"")
A80: INV-20250079 | B80: C009 | C80: =INDEX(Customers!$B$2:$B$11,MATCH(B80,Customers!$A$2:$A$11,0)) -> Prime Events | D80: 46001 | E80: =INDEX(Customers!$D$2:$D$11,MATCH(B80,Customers!$A$2:$A$11,0)) -> 15 | F80: =D80+E80 -> 46016 | G80: 29190 | H80: 21890 | I80: 46016 | J80: =G80-H80 -> 7300 | K80: =IF(AND(J80>0,Assumptions!$B$2>F80),Assumptions!$B$2-F80,0) -> 6 | L80: =IF(J80<=0,"Paid",IF(K80=0,"Not due",IF(K80<=30,"1-30",IF(K80<=60,"31-60",IF(K80<=90,"61-90","90+"))))) -> 1-30 | M80: =IF(AND(J80<=0,I80<>""),I80-D80,"")
A81: INV-20250080 | B81: C009 | C81: =INDEX(Customers!$B$2:$B$11,MATCH(B81,Customers!$A$2:$A$11,0)) -> Prime Events | D81: 46004 | E81: =INDEX(Customers!$D$2:$D$11,MATCH(B81,Customers!$A$2:$A$11,0)) -> 15 | F81: =D81+E81 -> 46019 | G81: 28860 | H81: 28860 | I81: 46014 | J81: =G81-H81 -> 0 | K81: =IF(AND(J81>0,Assumptions!$B$2>F81),Assumptions!$B$2-F81,0) -> 0 | L81: =IF(J81<=0,"Paid",IF(K81=0,"Not due",IF(K81<=30,"1-30",IF(K81<=60,"31-60",IF(K81<=90,"61-90","90+"))))) -> Paid | M81: =IF(AND(J81<=0,I81<>""),I81-D81,"") -> 10
A82: INV-20250081 | B82: C009 | C82: =INDEX(Customers!$B$2:$B$11,MATCH(B82,Customers!$A$2:$A$11,0)) -> Prime Events | D82: 46004 | E82: =INDEX(Customers!$D$2:$D$11,MATCH(B82,Customers!$A$2:$A$11,0)) -> 15 | F82: =D82+E82 -> 46019 | G82: 29820 | H82: 29820 | I82: 46014 | J82: =G82-H82 -> 0 | K82: =IF(AND(J82>0,Assumptions!$B$2>F82),Assumptions!$B$2-F82,0) -> 0 | L82: =IF(J82<=0,"Paid",IF(K82=0,"Not due",IF(K82<=30,"1-30",IF(K82<=60,"31-60",IF(K82<=90,"61-90","90+"))))) -> Paid | M82: =IF(AND(J82<=0,I82<>""),I82-D82,"") -> 10
A83: INV-20250082 | B83: C006 | C83: =INDEX(Customers!$B$2:$B$11,MATCH(B83,Customers!$A$2:$A$11,0)) -> Harbor Developers | D83: 46007 | E83: =INDEX(Customers!$D$2:$D$11,MATCH(B83,Customers!$A$2:$A$11,0)) -> 60 | F83: =D83+E83 -> 46067 | G83: 40910 | H83: 0 | J83: =G83-H83 -> 40910 | K83: =IF(AND(J83>0,Assumptions!$B$2>F83),Assumptions!$B$2-F83,0) -> 0 | L83: =IF(J83<=0,"Paid",IF(K83=0,"Not due",IF(K83<=30,"1-30",IF(K83<=60,"31-60",IF(K83<=90,"61-90","90+"))))) -> Not due | M83: =IF(AND(J83<=0,I83<>""),I83-D83,"")
A84: INV-20250083 | B84: C010 | C84: =INDEX(Customers!$B$2:$B$11,MATCH(B84,Customers!$A$2:$A$11,0)) -> Oasis Retail Group | D84: 46010 | E84: =INDEX(Customers!$D$2:$D$11,MATCH(B84,Customers!$A$2:$A$11,0)) -> 30 | F84: =D84+E84 -> 46040 | G84: 16230 | H84: 0 | J84: =G84-H84 -> 16230 | K84: =IF(AND(J84>0,Assumptions!$B$2>F84),Assumptions!$B$2-F84,0) -> 0 | L84: =IF(J84<=0,"Paid",IF(K84=0,"Not due",IF(K84<=30,"1-30",IF(K84<=60,"31-60",IF(K84<=90,"61-90","90+"))))) -> Not due | M84: =IF(AND(J84<=0,I84<>""),I84-D84,"")
A85: INV-20250084 | B85: C004 | C85: =INDEX(Customers!$B$2:$B$11,MATCH(B85,Customers!$A$2:$A$11,0)) -> Desert Logistics | D85: 46010 | E85: =INDEX(Customers!$D$2:$D$11,MATCH(B85,Customers!$A$2:$A$11,0)) -> 30 | F85: =D85+E85 -> 46040 | G85: 40280 | H85: 0 | J85: =G85-H85 -> 40280 | K85: =IF(AND(J85>0,Assumptions!$B$2>F85),Assumptions!$B$2-F85,0) -> 0 | L85: =IF(J85<=0,"Paid",IF(K85=0,"Not due",IF(K85<=30,"1-30",IF(K85<=60,"31-60",IF(K85<=90,"61-90","90+"))))) -> Not due | M85: =IF(AND(J85<=0,I85<>""),I85-D85,"")
A86: INV-20250085 | B86: C004 | C86: =INDEX(Customers!$B$2:$B$11,MATCH(B86,Customers!$A$2:$A$11,0)) -> Desert Logistics | D86: 46013 | E86: =INDEX(Customers!$D$2:$D$11,MATCH(B86,Customers!$A$2:$A$11,0)) -> 30 | F86: =D86+E86 -> 46043 | G86: 8570 | H86: 0 | J86: =G86-H86 -> 8570 | K86: =IF(AND(J86>0,Assumptions!$B$2>F86),Assumptions!$B$2-F86,0) -> 0 | L86: =IF(J86<=0,"Paid",IF(K86=0,"Not due",IF(K86<=30,"1-30",IF(K86<=60,"31-60",IF(K86<=90,"61-90","90+"))))) -> Not due | M86: =IF(AND(J86<=0,I86<>""),I86-D86,"")
A87: INV-20250086 | B87: C007 | C87: =INDEX(Customers!$B$2:$B$11,MATCH(B87,Customers!$A$2:$A$11,0)) -> Sunrise Facilities | D87: 46016 | E87: =INDEX(Customers!$D$2:$D$11,MATCH(B87,Customers!$A$2:$A$11,0)) -> 30 | F87: =D87+E87 -> 46046 | G87: 25820 | H87: 0 | J87: =G87-H87 -> 25820 | K87: =IF(AND(J87>0,Assumptions!$B$2>F87),Assumptions!$B$2-F87,0) -> 0 | L87: =IF(J87<=0,"Paid",IF(K87=0,"Not due",IF(K87<=30,"1-30",IF(K87<=60,"31-60",IF(K87<=90,"61-90","90+"))))) -> Not due | M87: =IF(AND(J87<=0,I87<>""),I87-D87,"")
A88: INV-20250087 | B88: C003 | C88: =INDEX(Customers!$B$2:$B$11,MATCH(B88,Customers!$A$2:$A$11,0)) -> Metro Utilities Co | D88: 46016 | E88: =INDEX(Customers!$D$2:$D$11,MATCH(B88,Customers!$A$2:$A$11,0)) -> 60 | F88: =D88+E88 -> 46076 | G88: 11430 | H88: 0 | J88: =G88-H88 -> 11430 | K88: =IF(AND(J88>0,Assumptions!$B$2>F88),Assumptions!$B$2-F88,0) -> 0 | L88: =IF(J88<=0,"Paid",IF(K88=0,"Not due",IF(K88<=30,"1-30",IF(K88<=60,"31-60",IF(K88<=90,"61-90","90+"))))) -> Not due | M88: =IF(AND(J88<=0,I88<>""),I88-D88,"")
A89: INV-20250088 | B89: C004 | C89: =INDEX(Customers!$B$2:$B$11,MATCH(B89,Customers!$A$2:$A$11,0)) -> Desert Logistics | D89: 46019 | E89: =INDEX(Customers!$D$2:$D$11,MATCH(B89,Customers!$A$2:$A$11,0)) -> 30 | F89: =D89+E89 -> 46049 | G89: 26940 | H89: 0 | J89: =G89-H89 -> 26940 | K89: =IF(AND(J89>0,Assumptions!$B$2>F89),Assumptions!$B$2-F89,0) -> 0 | L89: =IF(J89<=0,"Paid",IF(K89=0,"Not due",IF(K89<=30,"1-30",IF(K89<=60,"31-60",IF(K89<=90,"61-90","90+"))))) -> Not due | M89: =IF(AND(J89<=0,I89<>""),I89-D89,"")
A90: INV-20250089 | B90: C006 | C90: =INDEX(Customers!$B$2:$B$11,MATCH(B90,Customers!$A$2:$A$11,0)) -> Harbor Developers | D90: 46022 | E90: =INDEX(Customers!$D$2:$D$11,MATCH(B90,Customers!$A$2:$A$11,0)) -> 60 | F90: =D90+E90 -> 46082 | G90: 7850 | H90: 0 | J90: =G90-H90 -> 7850 | K90: =IF(AND(J90>0,Assumptions!$B$2>F90),Assumptions!$B$2-F90,0) -> 0 | L90: =IF(J90<=0,"Paid",IF(K90=0,"Not due",IF(K90<=30,"1-30",IF(K90<=60,"31-60",IF(K90<=90,"61-90","90+"))))) -> Not due | M90: =IF(AND(J90<=0,I90<>""),I90-D90,"")
A91: INV-20250090 | B91: C009 | C91: =INDEX(Customers!$B$2:$B$11,MATCH(B91,Customers!$A$2:$A$11,0)) -> Prime Events | D91: 46022 | E91: =INDEX(Customers!$D$2:$D$11,MATCH(B91,Customers!$A$2:$A$11,0)) -> 15 | F91: =D91+E91 -> 46037 | G91: 44940 | H91: 0 | J91: =G91-H91 -> 44940 | K91: =IF(AND(J91>0,Assumptions!$B$2>F91),Assumptions!$B$2-F91,0) -> 0 | L91: =IF(J91<=0,"Paid",IF(K91=0,"Not due",IF(K91<=30,"1-30",IF(K91<=60,"31-60",IF(K91<=90,"61-90","90+"))))) -> Not due | M91: =IF(AND(J91<=0,I91<>""),I91-D91,"")

Sheet AR_Aging
A1: Accounts Receivable Ageing Report
A2: As of: | B2: =Assumptions!$B$2 -> 46022
A4: Customer ID | B4: Customer Name | C4: Not due | D4: 1-30 | E4: 31-60 | F4: 61-90 | G4: 90+ | H4: Total AR ($) | I4: Credit Limit ($) | J4: % Overdue | K4: Credit Status
A5: =Customers!A2 -> C001 | B5: =Customers!B2 -> Al Noor Construction | C5: =SUMIFS(Invoices!$J$2:$J$91,Invoices!$B$2:$B$91,$A5,Invoices!$L$2:$L$91,"Not due") -> 0 | D5: =SUMIFS(Invoices!$J$2:$J$91,Invoices!$B$2:$B$91,$A5,Invoices!$L$2:$L$91,"1-30") -> 0 | E5: =SUMIFS(Invoices!$J$2:$J$91,Invoices!$B$2:$B$91,$A5,Invoices!$L$2:$L$91,"31-60") -> 0 | F5: =SUMIFS(Invoices!$J$2:$J$91,Invoices!$B$2:$B$91,$A5,Invoices!$L$2:$L$91,"61-90") -> 0 | G5: =SUMIFS(Invoices!$J$2:$J$91,Invoices!$B$2:$B$91,$A5,Invoices!$L$2:$L$91,"90+") -> 21750 | H5: =SUM(C5:G5) -> 21750 | I5: =Customers!E2 -> 150000 | J5: =IF(H5=0,0,SUM(D5:G5)/H5) -> 1 | K5: =IF(H5>I5,"Over limit",IF(G5>0,"Review 90+","OK")) -> Review 90+
A6: =Customers!A3 -> C002 | B6: =Customers!B3 -> Gulf Infra Projects | C6: =SUMIFS(Invoices!$J$2:$J$91,Invoices!$B$2:$B$91,$A6,Invoices!$L$2:$L$91,"Not due") -> 42090 | D6: =SUMIFS(Invoices!$J$2:$J$91,Invoices!$B$2:$B$91,$A6,Invoices!$L$2:$L$91,"1-30") -> 0 | E6: =SUMIFS(Invoices!$J$2:$J$91,Invoices!$B$2:$B$91,$A6,Invoices!$L$2:$L$91,"31-60") -> 9550 | F6: =SUMIFS(Invoices!$J$2:$J$91,Invoices!$B$2:$B$91,$A6,Invoices!$L$2:$L$91,"61-90") -> 0 | G6: =SUMIFS(Invoices!$J$2:$J$91,Invoices!$B$2:$B$91,$A6,Invoices!$L$2:$L$91,"90+") -> 0 | H6: =SUM(C6:G6) -> 51640 | I6: =Customers!E3 -> 250000 | J6: =IF(H6=0,0,SUM(D6:G6)/H6) -> 0.18493416 | K6: =IF(H6>I6,"Over limit",IF(G6>0,"Review 90+","OK")) -> OK
A7: =Customers!A4 -> C003 | B7: =Customers!B4 -> Metro Utilities Co | C7: =SUMIFS(Invoices!$J$2:$J$91,Invoices!$B$2:$B$91,$A7,Invoices!$L$2:$L$91,"Not due") -> 23970 | D7: =SUMIFS(Invoices!$J$2:$J$91,Invoices!$B$2:$B$91,$A7,Invoices!$L$2:$L$91,"1-30") -> 20020 | E7: =SUMIFS(Invoices!$J$2:$J$91,Invoices!$B$2:$B$91,$A7,Invoices!$L$2:$L$91,"31-60") -> 36320 | F7: =SUMIFS(Invoices!$J$2:$J$91,Invoices!$B$2:$B$91,$A7,Invoices!$L$2:$L$91,"61-90") -> 0 | G7: =SUMIFS(Invoices!$J$2:$J$91,Invoices!$B$2:$B$91,$A7,Invoices!$L$2:$L$91,"90+") -> 0 | H7: =SUM(C7:G7) -> 80310 | I7: =Customers!E4 -> 200000 | J7: =IF(H7=0,0,SUM(D7:G7)/H7) -> 0.70153157 | K7: =IF(H7>I7,"Over limit",IF(G7>0,"Review 90+","OK")) -> OK
A8: =Customers!A5 -> C004 | B8: =Customers!B5 -> Desert Logistics | C8: =SUMIFS(Invoices!$J$2:$J$91,Invoices!$B$2:$B$91,$A8,Invoices!$L$2:$L$91,"Not due") -> 75790 | D8: =SUMIFS(Invoices!$J$2:$J$91,Invoices!$B$2:$B$91,$A8,Invoices!$L$2:$L$91,"1-30") -> 0 | E8: =SUMIFS(Invoices!$J$2:$J$91,Invoices!$B$2:$B$91,$A8,Invoices!$L$2:$L$91,"31-60") -> 0 | F8: =SUMIFS(Invoices!$J$2:$J$91,Invoices!$B$2:$B$91,$A8,Invoices!$L$2:$L$91,"61-90") -> 0 | G8: =SUMIFS(Invoices!$J$2:$J$91,Invoices!$B$2:$B$91,$A8,Invoices!$L$2:$L$91,"90+") -> 16610 | H8: =SUM(C8:G8) -> 92400 | I8: =Customers!E5 -> 80000 | J8: =IF(H8=0,0,SUM(D8:G8)/H8) -> 0.1797619 | K8: =IF(H8>I8,"Over limit",IF(G8>0,"Review 90+","OK")) -> Over limit
A9: =Customers!A6 -> C005 | B9: =Customers!B6 -> BlueWave Telecom | C9: =SUMIFS(Invoices!$J$2:$J$91,Invoices!$B$2:$B$91,$A9,Invoices!$L$2:$L$91,"Not due") -> 21780 | D9: =SUMIFS(Invoices!$J$2:$J$91,Invoices!$B$2:$B$91,$A9,Invoices!$L$2:$L$91,"1-30") -> 0 | E9: =SUMIFS(Invoices!$J$2:$J$91,Invoices!$B$2:$B$91,$A9,Invoices!$L$2:$L$91,"31-60") -> 0 | F9: =SUMIFS(Invoices!$J$2:$J$91,Invoices!$B$2:$B$91,$A9,Invoices!$L$2:$L$91,"61-90") -> 0 | G9: =SUMIFS(Invoices!$J$2:$J$91,Invoices!$B$2:$B$91,$A9,Invoices!$L$2:$L$91,"90+") -> 0 | H9: =SUM(C9:G9) -> 21780 | I9: =Customers!E6 -> 120000 | J9: =IF(H9=0,0,SUM(D9:G9)/H9) -> 0 | K9: =IF(H9>I9,"Over limit",IF(G9>0,"Review 90+","OK")) -> OK
A10: =Customers!A7 -> C006 | B10: =Customers!B7 -> Harbor Developers | C10: =SUMIFS(Invoices!$J$2:$J$91,Invoices!$B$2:$B$91,$A10,Invoices!$L$2:$L$91,"Not due") -> 82150 | D10: =SUMIFS(Invoices!$J$2:$J$91,Invoices!$B$2:$B$91,$A10,Invoices!$L$2:$L$91,"1-30") -> 6140 | E10: =SUMIFS(Invoices!$J$2:$J$91,Invoices!$B$2:$B$91,$A10,Invoices!$L$2:$L$91,"31-60") -> 0 | F10: =SUMIFS(Invoices!$J$2:$J$91,Invoices!$B$2:$B$91,$A10,Invoices!$L$2:$L$91,"61-90") -> 0 | G10: =SUMIFS(Invoices!$J$2:$J$91,Invoices!$B$2:$B$91,$A10,Invoices!$L$2:$L$91,"90+") -> 0 | H10: =SUM(C10:G10) -> 88290 | I10: =Customers!E7 -> 180000 | J10: =IF(H10=0,0,SUM(D10:G10)/H10) -> 0.06954355 | K10: =IF(H10>I10,"Over limit",IF(G10>0,"Review 90+","OK")) -> OK
A11: =Customers!A8 -> C007 | B11: =Customers!B8 -> Sunrise Facilities | C11: =SUMIFS(Invoices!$J$2:$J$91,Invoices!$B$2:$B$91,$A11,Invoices!$L$2:$L$91,"Not due") -> 25820 | D11: =SUMIFS(Invoices!$J$2:$J$91,Invoices!$B$2:$B$91,$A11,Invoices!$L$2:$L$91,"1-30") -> 0 | E11: =SUMIFS(Invoices!$J$2:$J$91,Invoices!$B$2:$B$91,$A11,Invoices!$L$2:$L$91,"31-60") -> 0 | F11: =SUMIFS(Invoices!$J$2:$J$91,Invoices!$B$2:$B$91,$A11,Invoices!$L$2:$L$91,"61-90") -> 0 | G11: =SUMIFS(Invoices!$J$2:$J$91,Invoices!$B$2:$B$91,$A11,Invoices!$L$2:$L$91,"90+") -> 2430 | H11: =SUM(C11:G11) -> 28250 | I11: =Customers!E8 -> 60000 | J11: =IF(H11=0,0,SUM(D11:G11)/H11) -> 0.086017699 | K11: =IF(H11>I11,"Over limit",IF(G11>0,"Review 90+","OK")) -> Review 90+
A12: =Customers!A9 -> C008 | B12: =Customers!B9 -> Coastal Roads Authority | C12: =SUMIFS(Invoices!$J$2:$J$91,Invoices!$B$2:$B$91,$A12,Invoices!$L$2:$L$91,"Not due") -> 158410 | D12: =SUMIFS(Invoices!$J$2:$J$91,Invoices!$B$2:$B$91,$A12,Invoices!$L$2:$L$91,"1-30") -> 89940 | E12: =SUMIFS(Invoices!$J$2:$J$91,Invoices!$B$2:$B$91,$A12,Invoices!$L$2:$L$91,"31-60") -> 26490 | F12: =SUMIFS(Invoices!$J$2:$J$91,Invoices!$B$2:$B$91,$A12,Invoices!$L$2:$L$91,"61-90") -> 0 | G12: =SUMIFS(Invoices!$J$2:$J$91,Invoices!$B$2:$B$91,$A12,Invoices!$L$2:$L$91,"90+") -> 0 | H12: =SUM(C12:G12) -> 274840 | I12: =Customers!E9 -> 300000 | J12: =IF(H12=0,0,SUM(D12:G12)/H12) -> 0.42362829 | K12: =IF(H12>I12,"Over limit",IF(G12>0,"Review 90+","OK")) -> OK
A13: =Customers!A10 -> C009 | B13: =Customers!B10 -> Prime Events | C13: =SUMIFS(Invoices!$J$2:$J$91,Invoices!$B$2:$B$91,$A13,Invoices!$L$2:$L$91,"Not due") -> 44940 | D13: =SUMIFS(Invoices!$J$2:$J$91,Invoices!$B$2:$B$91,$A13,Invoices!$L$2:$L$91,"1-30") -> 7300 | E13: =SUMIFS(Invoices!$J$2:$J$91,Invoices!$B$2:$B$91,$A13,Invoices!$L$2:$L$91,"31-60") -> 11000 | F13: =SUMIFS(Invoices!$J$2:$J$91,Invoices!$B$2:$B$91,$A13,Invoices!$L$2:$L$91,"61-90") -> 0 | G13: =SUMIFS(Invoices!$J$2:$J$91,Invoices!$B$2:$B$91,$A13,Invoices!$L$2:$L$91,"90+") -> 5190 | H13: =SUM(C13:G13) -> 68430 | I13: =Customers!E10 -> 40000 | J13: =IF(H13=0,0,SUM(D13:G13)/H13) -> 0.3432705 | K13: =IF(H13>I13,"Over limit",IF(G13>0,"Review 90+","OK")) -> Over limit
A14: =Customers!A11 -> C010 | B14: =Customers!B11 -> Oasis Retail Group | C14: =SUMIFS(Invoices!$J$2:$J$91,Invoices!$B$2:$B$91,$A14,Invoices!$L$2:$L$91,"Not due") -> 16230 | D14: =SUMIFS(Invoices!$J$2:$J$91,Invoices!$B$2:$B$91,$A14,Invoices!$L$2:$L$91,"1-30") -> 11750 | E14: =SUMIFS(Invoices!$J$2:$J$91,Invoices!$B$2:$B$91,$A14,Invoices!$L$2:$L$91,"31-60") -> 0 | F14: =SUMIFS(Invoices!$J$2:$J$91,Invoices!$B$2:$B$91,$A14,Invoices!$L$2:$L$91,"61-90") -> 0 | G14: =SUMIFS(Invoices!$J$2:$J$91,Invoices!$B$2:$B$91,$A14,Invoices!$L$2:$L$91,"90+") -> 1580 | H14: =SUM(C14:G14) -> 29560 | I14: =Customers!E11 -> 70000 | J14: =IF(H14=0,0,SUM(D14:G14)/H14) -> 0.45094723 | K14: =IF(H14>I14,"Over limit",IF(G14>0,"Review 90+","OK")) -> Review 90+
B15: Total | C15: =SUM(C5:C14) -> 491180 | D15: =SUM(D5:D14) -> 135150 | E15: =SUM(E5:E14) -> 83360 | F15: =SUM(F5:F14) -> 0 | G15: =SUM(G5:G14) -> 47560 | H15: =SUM(H5:H14) -> 757250 | I15: =SUM(I5:I14) -> 1450000 | J15: =IF(H15=0,0,SUM(D15:G15)/H15) -> 0.35136349
B16: % of total AR | C16: =IF($H$15=0,0,C15/$H$15) -> 0.64863651 | D16: =IF($H$15=0,0,D15/$H$15) -> 0.17847474 | E16: =IF($H$15=0,0,E15/$H$15) -> 0.11008254 | F16: =IF($H$15=0,0,F15/$H$15) -> 0 | G16: =IF($H$15=0,0,G15/$H$15) -> 0.062806207

Sheet Collections_KPI
A1: Monthly Billing, Collections & Collection Effectiveness
A3: Month start | B3: Month end | C3: Billed ($) | D3: Collected ($) | E3: Opening AR ($) | F3: Closing AR ($) | G3: CEI % | H3: Coll./Billed
A4: 45839 | B4: =EOMONTH(A4,0) -> 45869 | C4: =SUMIFS(Invoices!$G$2:$G$91,Invoices!$D$2:$D$91,">="&A4,Invoices!$D$2:$D$91,"<="&B4) -> 297690 | D4: =SUMIFS(Invoices!$H$2:$H$91,Invoices!$I$2:$I$91,">="&A4,Invoices!$I$2:$I$91,"<="&B4) -> 105490 | E4: 0 | F4: =E4+C4-D4 -> 192200 | G4: =IF((E4+C4)=0,0,D4/(E4+C4)) -> 0.35436192 | H4: =IF(C4=0,0,D4/C4) -> 0.35436192
A5: 45870 | B5: =EOMONTH(A5,0) -> 45900 | C5: =SUMIFS(Invoices!$G$2:$G$91,Invoices!$D$2:$D$91,">="&A5,Invoices!$D$2:$D$91,"<="&B5) -> 246140 | D5: =SUMIFS(Invoices!$H$2:$H$91,Invoices!$I$2:$I$91,">="&A5,Invoices!$I$2:$I$91,"<="&B5) -> 73150 | E5: =F4 -> 192200 | F5: =E5+C5-D5 -> 365190 | G5: =IF((E5+C5)=0,0,D5/(E5+C5)) -> 0.16687959 | H5: =IF(C5=0,0,D5/C5) -> 0.29718859
A6: 45901 | B6: =EOMONTH(A6,0) -> 45930 | C6: =SUMIFS(Invoices!$G$2:$G$91,Invoices!$D$2:$D$91,">="&A6,Invoices!$D$2:$D$91,"<="&B6) -> 386680 | D6: =SUMIFS(Invoices!$H$2:$H$91,Invoices!$I$2:$I$91,">="&A6,Invoices!$I$2:$I$91,"<="&B6) -> 203050 | E6: =F5 -> 365190 | F6: =E6+C6-D6 -> 548820 | G6: =IF((E6+C6)=0,0,D6/(E6+C6)) -> 0.27005998 | H6: =IF(C6=0,0,D6/C6) -> 0.5251112
A7: 45931 | B7: =EOMONTH(A7,0) -> 45961 | C7: =SUMIFS(Invoices!$G$2:$G$91,Invoices!$D$2:$D$91,">="&A7,Invoices!$D$2:$D$91,"<="&B7) -> 365960 | D7: =SUMIFS(Invoices!$H$2:$H$91,Invoices!$I$2:$I$91,">="&A7,Invoices!$I$2:$I$91,"<="&B7) -> 225280 | E7: =F6 -> 548820 | F7: =E7+C7-D7 -> 689500 | G7: =IF((E7+C7)=0,0,D7/(E7+C7)) -> 0.24626686 | H7: =IF(C7=0,0,D7/C7) -> 0.6155864
A8: 45962 | B8: =EOMONTH(A8,0) -> 45991 | C8: =SUMIFS(Invoices!$G$2:$G$91,Invoices!$D$2:$D$91,">="&A8,Invoices!$D$2:$D$91,"<="&B8) -> 322890 | D8: =SUMIFS(Invoices!$H$2:$H$91,Invoices!$I$2:$I$91,">="&A8,Invoices!$I$2:$I$91,"<="&B8) -> 373980 | E8: =F7 -> 689500 | F8: =E8+C8-D8 -> 638410 | G8: =IF((E8+C8)=0,0,D8/(E8+C8)) -> 0.3694031 | H8: =IF(C8=0,0,D8/C8) -> 1.1582273
A9: 45992 | B9: =EOMONTH(A9,0) -> 46022 | C9: =SUMIFS(Invoices!$G$2:$G$91,Invoices!$D$2:$D$91,">="&A9,Invoices!$D$2:$D$91,"<="&B9) -> 415230 | D9: =SUMIFS(Invoices!$H$2:$H$91,Invoices!$I$2:$I$91,">="&A9,Invoices!$I$2:$I$91,"<="&B9) -> 296390 | E9: =F8 -> 638410 | F9: =E9+C9-D9 -> 757250 | G9: =IF((E9+C9)=0,0,D9/(E9+C9)) -> 0.28130101 | H9: =IF(C9=0,0,D9/C9) -> 0.71379717
A10: Total | C10: =SUM(C4:C9) -> 2034590 | D10: =SUM(D4:D9) -> 1277340
A13: Note: CEI here = collections ÷ (opening AR + billings) for the month — a simplified effectiveness measure.
A15: Key ratios
A16: Total AR at report date ($) | B16: =AR_Aging!H15 -> 757250
A17: Credit sales in lookback period ($) | B17: =SUMIFS(Invoices!$G$2:$G$91,Invoices!$D$2:$D$91,">"&(Assumptions!$B$2-Assumptions!$B$3),Invoices!$D$2:$D$91,"<="&Assumptions!$B$2) -> 1061180
A18: DSO (days) | B18: =IF(B17=0,0,B16/B17*Assumptions!$B$3) -> 64.223317
A19: Overdue AR ($) | B19: =SUM(AR_Aging!D15:G15) -> 266070
A20: % AR overdue | B20: =IF(B16=0,0,B19/B16) -> 0.35136349
A21: AR over 90 days ($) | B21: =AR_Aging!G15 -> 47560
A22: Average days to pay (paid invoices) | B22: =AVERAGE(Invoices!$M$2:$M$91) -> 40.384615
A23: Invoices issued (count) | B23: =COUNTA(Invoices!$A$2:$A$91) -> 90
A24: Invoices fully paid (count) | B24: =COUNTIF(Invoices!$L$2:$L$91,"Paid") -> 52
A25: 6-month CEI | B25: =IF((E4+C10)=0,0,D10/(E4+C10)) -> 0.62781199

Sheet Cash_Forecast
A1: Expected Cash Collections — next 3 months
A2: Month start → | B2: 46023 | C2: 46054 | D2: 46082
A3: Source | B3: Jan-26 ($) | C3: Feb-26 ($) | D3: Mar-26 ($) | E3: Total ($)
A4: Not-yet-due invoices (by due date) | B4: =SUMIFS(Invoices!$J$2:$J$91,Invoices!$L$2:$L$91,"Not due",Invoices!$F$2:$F$91,">="&MIN(B$2,Assumptions!$B$2),Invoices!$F$2:$F$91,"<="&EOMONTH(B$2,0))*Assumptions!$B$4 -> 252761.6 | C4: =SUMIFS(Invoices!$J$2:$J$91,Invoices!$L$2:$L$91,"Not due",Invoices!$F$2:$F$91,">="&C$2,Invoices!$F$2:$F$91,"<="&EOMONTH(C$2,0))*Assumptions!$B$4 -> 187875.8 | D4: =SUMIFS(Invoices!$J$2:$J$91,Invoices!$L$2:$L$91,"Not due",Invoices!$F$2:$F$91,">="&D$2,Invoices!$F$2:$F$91,"<="&EOMONTH(D$2,0))*Assumptions!$B$4 -> 40719 | E4: =SUM(B4:D4) -> 481356.4
A5: Overdue 1-30 days (collected after delay) | B5: =IF(Assumptions!$B$2+Assumptions!$B$9<=EOMONTH(B$2,0),SUMIFS(Invoices!$J$2:$J$91,Invoices!$L$2:$L$91,"1-30")*Assumptions!$B$5,0) -> 128392.5 | C5: =IF(AND(Assumptions!$B$2+Assumptions!$B$9>EOMONTH(B$2,0),Assumptions!$B$2+Assumptions!$B$9<=EOMONTH(C$2,0)),SUMIFS(Invoices!$J$2:$J$91,Invoices!$L$2:$L$91,"1-30")*Assumptions!$B$5,0) -> 0 | D5: =IF(AND(Assumptions!$B$2+Assumptions!$B$9>EOMONTH(C$2,0),Assumptions!$B$2+Assumptions!$B$9<=EOMONTH(D$2,0)),SUMIFS(Invoices!$J$2:$J$91,Invoices!$L$2:$L$91,"1-30")*Assumptions!$B$5,0) -> 0 | E5: =SUM(B5:D5) -> 128392.5
A6: Overdue 31-60 days (collected after delay) | B6: =IF(Assumptions!$B$2+Assumptions!$B$9<=EOMONTH(B$2,0),SUMIFS(Invoices!$J$2:$J$91,Invoices!$L$2:$L$91,"31-60")*Assumptions!$B$6,0) -> 70856 | C6: =IF(AND(Assumptions!$B$2+Assumptions!$B$9>EOMONTH(B$2,0),Assumptions!$B$2+Assumptions!$B$9<=EOMONTH(C$2,0)),SUMIFS(Invoices!$J$2:$J$91,Invoices!$L$2:$L$91,"31-60")*Assumptions!$B$6,0) -> 0 | D6: =IF(AND(Assumptions!$B$2+Assumptions!$B$9>EOMONTH(C$2,0),Assumptions!$B$2+Assumptions!$B$9<=EOMONTH(D$2,0)),SUMIFS(Invoices!$J$2:$J$91,Invoices!$L$2:$L$91,"31-60")*Assumptions!$B$6,0) -> 0 | E6: =SUM(B6:D6) -> 70856
A7: Overdue 61-90 days (collected after delay) | B7: =IF(Assumptions!$B$2+Assumptions!$B$9<=EOMONTH(B$2,0),SUMIFS(Invoices!$J$2:$J$91,Invoices!$L$2:$L$91,"61-90")*Assumptions!$B$7,0) -> 0 | C7: =IF(AND(Assumptions!$B$2+Assumptions!$B$9>EOMONTH(B$2,0),Assumptions!$B$2+Assumptions!$B$9<=EOMONTH(C$2,0)),SUMIFS(Invoices!$J$2:$J$91,Invoices!$L$2:$L$91,"61-90")*Assumptions!$B$7,0) -> 0 | D7: =IF(AND(Assumptions!$B$2+Assumptions!$B$9>EOMONTH(C$2,0),Assumptions!$B$2+Assumptions!$B$9<=EOMONTH(D$2,0)),SUMIFS(Invoices!$J$2:$J$91,Invoices!$L$2:$L$91,"61-90")*Assumptions!$B$7,0) -> 0 | E7: =SUM(B7:D7) -> 0
A8: Overdue 90+ days (collected after delay) | B8: =IF(Assumptions!$B$2+Assumptions!$B$9<=EOMONTH(B$2,0),SUMIFS(Invoices!$J$2:$J$91,Invoices!$L$2:$L$91,"90+")*Assumptions!$B$8,0) -> 14268 | C8: =IF(AND(Assumptions!$B$2+Assumptions!$B$9>EOMONTH(B$2,0),Assumptions!$B$2+Assumptions!$B$9<=EOMONTH(C$2,0)),SUMIFS(Invoices!$J$2:$J$91,Invoices!$L$2:$L$91,"90+")*Assumptions!$B$8,0) -> 0 | D8: =IF(AND(Assumptions!$B$2+Assumptions!$B$9>EOMONTH(C$2,0),Assumptions!$B$2+Assumptions!$B$9<=EOMONTH(D$2,0)),SUMIFS(Invoices!$J$2:$J$91,Invoices!$L$2:$L$91,"90+")*Assumptions!$B$8,0) -> 0 | E8: =SUM(B8:D8) -> 14268
A9: Total expected collections | B9: =SUM(B4:B8) -> 466278.1 | C9: =SUM(C4:C8) -> 187875.8 | D9: =SUM(D4:D8) -> 40719 | E9: =SUM(E4:E8) -> 694872.9
A11: At-risk balance (not expected to be collected) ($) | B11: =AR_Aging!H15-E9-B13 -> 62377.1
A12: Note: Not-due invoices falling due after Mar-26 are excluded from this 3-month view.
A13: Check: not-due balance falling after Mar-26 ($) | B13: =SUMIFS(Invoices!$J$2:$J$91,Invoices!$L$2:$L$91,"Not due",Invoices!$F$2:$F$91,">"&EOMONTH($D$2,0)) -> 0
